Nectrlline/__init__.py
Nectrlline/line.py
line/py/line.py
amzon.line-1.0.0.dist-info/METADATA
amzon.line-1.0.0.dist-info/WHEEL
amzon.line-1.0.0.dist-info/entry_points.txt
amzon.line-1.0.0.dist-info/top_level.txt
amzon.line-1.0.0.dist-info/RECORD
