Metadata-Version: 2.1
Name: amzon.line
Version: 1.0.0
Summary: LINE Location List
Home-page: https://github.com/takezyou/pydata
Author: takezyou
Author-email: kaitokun07@icloud.com
License: MIT
Keywords: lineamzon
Platform: UNKNOWN
Classifier: License :: OSI Approved :: MIT License
Classifier: Programming Language :: Python :: 3.8
Classifier: Programming Language :: Python :: 3.7
Requires-Dist: requests
